deploy/__init__.py
deploy/deploy_obproject.py
highlight_card/__init__.py
highlight_card/highlight_decorator.py
metaflow_extensions/obproject_utils/__init__.py
metaflow_extensions/obproject_utils/plugins/mfextinit_highlight.py
metaflow_extensions/obproject_utils/plugins/cards/highlight/__init__.py
metaflow_extensions/obproject_utils/plugins/cards/highlight/base.html
metaflow_extensions/obproject_utils/plugins/highlight/__init__.py
metaflow_extensions/obproject_utils/plugins/highlight/highlight_decorator.py
obproject/__init__.py
obproject/assets.py
obproject/evals_logger.py
obproject/project_events.py
obproject/projectbase.py
ob_project_utils-0.2.17.dist-info/METADATA
ob_project_utils-0.2.17.dist-info/WHEEL
ob_project_utils-0.2.17.dist-info/entry_points.txt
ob_project_utils-0.2.17.dist-info/top_level.txt
ob_project_utils-0.2.17.dist-info/RECORD
