Metadata-Version: 2.4
Name: ob-project-utils
Version: 0.2.17
Summary: Utilities for Outerbounds projects
Author: Ville Tuulos
Author-email: ville@outerbounds.co
Requires-Dist: requests
Requires-Dist: toml; python_version < "3.11"
Dynamic: author
Dynamic: author-email
Dynamic: description
Dynamic: description-content-type
Dynamic: requires-dist
Dynamic: summary
